python_jam.py
python_jam-1.0.1.dist-info/WHEEL
python_jam-1.0.1.dist-info/METADATA
python_jam-1.0.1.dist-info/RECORD
