Metadata-Version: 2.1
Name: python-jam
Version: 1.0.1
Summary: Asynchronous python Library for justauthenticate.me authentication
License: MIT
Author: Rick Henry
Author-email: rickhenry@rickhenry.dev
Requires-Python: >=3.6,<4.0
Classifier: License :: OSI Approved :: MIT License
Classifier: Programming Language :: Python :: 3
Classifier: Programming Language :: Python :: 3.6
Classifier: Programming Language :: Python :: 3.7
Classifier: Programming Language :: Python :: 3.8
Classifier: Programming Language :: Python :: 3.9
Requires-Dist: aiohttp (>=3.7,<4.0)
Requires-Dist: python-jwt (>=3.3,<4.0)
